rcswitch.v
/*
 * The MIT License (MIT)
 *
 * Copyright (c) 2015 Stefan Wendler
 *
 * Permission is hereby granted, free of charge, to any person obtaining a copy
 * of this software and associated documentation files (the "Software"), to deal
 * in the Software without restriction, including without limitation the rights
 * to use, copy, modify, merge, publish, distribute, sublicense, and/or sell
 * copies of the Software, and to permit persons to whom the Software is
 * furnished to do so, subject to the following conditions:
 *
 * The above copyright notice and this permission notice shall be included in
 * all copies or substantial portions of the Software.
 *
 * THE SOFTWARE IS PROVIDED "AS IS", WITHOUT WARRANTY OF ANY KIND, EXPRESS OR
 * IMPLIED, INCLUDING BUT NOT LIMITED TO THE WARRANTIES OF MERCHANTABILITY,
 * FITNESS FOR A PARTICULAR PURPOSE AND NONINFRINGEMENT. IN NO EVENT SHALL THE
 * AUTHORS OR COPYRIGHT HOLDERS BE LIABLE FOR ANY CLAIM, DAMAGES OR OTHER
 * LIABILITY, WHETHER IN AN ACTION OF CONTRACT, TORT OR OTHERWISE, ARISING FROM,
 * OUT OF OR IN CONNECTION WITH THE SOFTWARE OR THE USE OR OTHER DEALINGS IN
 * THE SOFTWARE.
 */

/**
 * Module to send tri-state signals to a radio for operation a RC switch.
 * 
 * The following wavefroms are used for the tri-states (each pulse is 350us):
 *
 * Tri-state "0" Bit
 *            _     _
 *           | |___| |___
 *            1  3  1  3
 *
 * Tri-state "1" Bit
 *            ___   ___
 *           |   |_|   |_
 *             3  1  3  1
 *
 * Tri-state "F" Bit
 *            _     ___
 *           | |___|   |_
 *            1  3   3  1
 *
 * "Sync" Bit
 *            _
 *           | |_______________________________
 *            1 31
 * 
 * A message to an RC switch has the following format:
 * 
 * 	<address><channel><status>
 * 
 * 	<address> is a 5 bit field. Most switches use 11111 as default. 
 * 	<channel> is A, B, C, D 
 * 	<status>  is 0 (off) or 1 (on)
 * 
 * To turn channel A on the switch at address 11111 ON, the message would look like this:
 * 
 * 	11111A1
 * 
 * For the module, this needs to be translated to tri-state wave form like so:
 * 
 *  0 in tri-state is F => 10001110
 * 	1 in tri-state is 0 => 10001000
 * 	
 * Thus, the address 11111 is in tri-state: 10001000_10001000_10001000_10001000_10001000  
 * 
 * The channel translates like this:
 * 
 * 	A in tri-state is 0FFFF => 10001000_10001110_10001110_10001110_10001110
 * 	B in tri-state is F0FFF => 10001110_10001000_10001110_10001110_10001110
 *  C in tri-state is FF0FF => 10001110_10001110_10001000_10001110_10001110
 * 	D in tri-state is FFF0F => 10001110_10001110_10001110_10001000_10001110
 * 
 * Then the state could be mapped like this:
 * 
 * 	0/off in tri-state is 0F => 10001000_10001110
 * 	1/on  in tri-state is F0 => 10001110_10001000
 * 
 * And finally the sync bit is a constant:
 * 
 * 	sync => 10000000_00000000_00000000_00000000
 * 
 *****************************************************************************
 * Also it shold be noted, that a message needs to be sent multible times (2-10). 
 * Otherwise it is very likely that the switch will not work!
 *****************************************************************************
 * 
 * inputs:
 * 		clk			on the positive edge, the next bit is shifted to the radio
 * 					the clock needs to provide 350us per cycle (from rising 
 * 					edge to rising edge)
 * 		send		if set to 1, the complete message (addr+chan+stat+sync) is send
 * 					over and over again until send is set back to 0
 *		addr		the address in tri-state wave-form
 * 					e.g. 40'b10001000_10001000_10001000_10001000_10001000 = 11111
 * 		chan		the channel identifier in tri-state wave-form 
 * 				 	e.g. 40'b10001000_10001110_10001110_10001110_10001110 = chan A 
 * 		stat		the status in tri-state wave-form
 * 					e.g. 16'b10001000_10001110 = ON 
 * 		sync		the sync bit in tri-state wave-form
 * 					e.g. 32'b10000000_00000000_00000000_00000000
 * outputs:
 * 		ready		1 if module is ready to send, 0 if sending is already in progrss
 * 		out			the bits shifted out to the radio
 */
module rcswitch_send(
	input clk, 
 	input send,
	input [39:0] addr,
	input [39:0] chan,
	input [15:0] stat,
	input [31:0] sync,
	output ready,
	output out 
	);

	reg r_out;
	reg r_ready;
	reg [7:0] pos;

	initial begin
		r_ready = 1;
		r_out 	= 0;
		pos 	= 0;
	end

	always @(posedge clk) begin
		
		// start a new message
		if(send && pos == 0) begin
			pos = 128;
			r_ready = 0;
		end
		// shift out the bits for the message
		else if(pos > 0) begin
			pos = pos - 1;
			
			if(pos < 128 && pos > 87) 
				r_out = (addr >> (pos - 88));
			else if(pos < 88 && pos > 47) 
				r_out = (chan >> (pos - 48));
			else if(pos < 48 && pos > 31) 
				r_out = (stat >> (pos - 32));
			else
				r_out = (sync >> pos) & 1'b1;
				
			// message is done - prepare for repeat
			if(pos == 0) begin
				r_ready = 1;
				r_out 	= 0;
				pos 	= 0;
			end
		end
	end

	assign ready = r_ready;
	assign out 	 = r_out;

endmodule

rcswitch_tb.v
/*
 * The MIT License (MIT)
 *
 * Copyright (c) 2015 Stefan Wendler
 *
 * Permission is hereby granted, free of charge, to any person obtaining a copy
 * of this software and associated documentation files (the "Software"), to deal
 * in the Software without restriction, including without limitation the rights
 * to use, copy, modify, merge, publish, distribute, sublicense, and/or sell
 * copies of the Software, and to permit persons to whom the Software is
 * furnished to do so, subject to the following conditions:
 *
 * The above copyright notice and this permission notice shall be included in
 * all copies or substantial portions of the Software.
 *
 * THE SOFTWARE IS PROVIDED "AS IS", WITHOUT WARRANTY OF ANY KIND, EXPRESS OR
 * IMPLIED, INCLUDING BUT NOT LIMITED TO THE WARRANTIES OF MERCHANTABILITY,
 * FITNESS FOR A PARTICULAR PURPOSE AND NONINFRINGEMENT. IN NO EVENT SHALL THE
 * AUTHORS OR COPYRIGHT HOLDERS BE LIABLE FOR ANY CLAIM, DAMAGES OR OTHER
 * LIABILITY, WHETHER IN AN ACTION OF CONTRACT, TORT OR OTHERWISE, ARISING FROM,
 * OUT OF OR IN CONNECTION WITH THE SOFTWARE OR THE USE OR OTHER DEALINGS IN
 * THE SOFTWARE.
 */

/**
 * Testbench for rcswitch_send.
 * 
 * I use this with iverilog and gtkwave:
 * 
 * 	iverilog -o rcswitch.vvp clockdiv.v rcswitch.v rcswitch_tb.v 	
 * 	./rcswitch.vvp
 * 	gtkwace rcswitch.vcd
 */
module rcswitch_test;

	reg [39:0] addr;
	reg [39:0] chan;
	reg [31:0] sync;
	reg [15:0] stat;
	reg send;

	initial begin
		#0   addr = 40'b10001000_10001000_10001000_10001000_10001000;	// 11111 
		#0   chan = 40'b10001000_10001110_10001110_10001110_10001110; 	// 0FFFF = A
		#0   stat = 16'b10001110_10001000;								// F0 = ON 
		#0   sync = 32'b10000000_00000000_00000000_00000000; 			// SYNC
		#2   send = 1;
		#100 send = 0;
		#300 $finish;
	end

	// clock 
	reg clk = 0;
	always #1 clk = !clk;

	wire ready;
	wire out;

	rcswitch_send rcswitch_send_inst (
		.clk(clk),
		.send(send),
		.addr(addr),
		.chan(chan),
		.stat(stat),
		.sync(sync),
		.ready(ready),
		.out(out)
	);

	initial
	begin
    	$dumpfile("rcswitch.vcd");
		$dumpvars(0, rcswitch_test);
	end

endmodule

rcswitch.vcd
$date
	Thu Feb  5 20:45:31 2015
$end
$version
	Icarus Verilog
$end
$timescale
	1s
$end
$scope module rcswitch_test $end
$var wire 1 ! out $end
$var wire 1 " ready $end
$var reg 40 # addr [39:0] $end
$var reg 40 $ chan [39:0] $end
$var reg 1 % clk $end
$var reg 1 & send $end
$var reg 16 ' stat [15:0] $end
$var reg 32 ( sync [31:0] $end
$scope module rcswitch_send_inst $end
$var wire 40 ) addr [39:0] $end
$var wire 40 * chan [39:0] $end
$var wire 1 + clk $end
$var wire 1 ! out $end
$var wire 1 " ready $end
$var wire 1 , send $end
$var wire 16 - stat [15:0] $end
$var wire 32 . sync [31:0] $end
$var reg 8 / pos [7:0] $end
$var reg 1 0 r_out $end
$var reg 1 1 r_ready $end
$upscope $end
$upscope $end
$enddefinitions $end
#0
$dumpvars
11
00
b0 /
b10000000000000000000000000000000 .
b1000111010001000 -
x,
0+
b1000100010001110100011101000111010001110 *
b1000100010001000100010001000100010001000 )
b10000000000000000000000000000000 (
b1000111010001000 '
x&
0%
b1000100010001110100011101000111010001110 $
b1000100010001000100010001000100010001000 #
1"
0!
$end
#1
1%
1+
#2
0%
0+
1&
1,
#3
01
0"
b10000000 /
1%
1+
#4
0%
0+
#5
10
1!
b1111111 /
1%
1+
#6
0%
0+
#7
00
0!
b1111110 /
1%
1+
#8
0%
0+
#9
b1111101 /
1%
1+
#10
0%
0+
#11
b1111100 /
1%
1+
#12
0%
0+
#13
10
1!
b1111011 /
1%
1+
#14
0%
0+
#15
00
0!
b1111010 /
1%
1+
#16
0%
0+
#17
b1111001 /
1%
1+
#18
0%
0+
#19
b1111000 /
1%
1+
#20
0%
0+
#21
10
1!
b1110111 /
1%
1+
#22
0%
0+
#23
00
0!
b1110110 /
1%
1+
#24
0%
0+
#25
b1110101 /
1%
1+
#26
0%
0+
#27
b1110100 /
1%
1+
#28
0%
0+
#29
10
1!
b1110011 /
1%
1+
#30
0%
0+
#31
00
0!
b1110010 /
1%
1+
#32
0%
0+
#33
b1110001 /
1%
1+
#34
0%
0+
#35
b1110000 /
1%
1+
#36
0%
0+
#37
10
1!
b1101111 /
1%
1+
#38
0%
0+
#39
00
0!
b1101110 /
1%
1+
#40
0%
0+
#41
b1101101 /
1%
1+
#42
0%
0+
#43
b1101100 /
1%
1+
#44
0%
0+
#45
10
1!
b1101011 /
1%
1+
#46
0%
0+
#47
00
0!
b1101010 /
1%
1+
#48
0%
0+
#49
b1101001 /
1%
1+
#50
0%
0+
#51
b1101000 /
1%
1+
#52
0%
0+
#53
10
1!
b1100111 /
1%
1+
#54
0%
0+
#55
00
0!
b1100110 /
1%
1+
#56
0%
0+
#57
b1100101 /
1%
1+
#58
0%
0+
#59
b1100100 /
1%
1+
#60
0%
0+
#61
10
1!
b1100011 /
1%
1+
#62
0%
0+
#63
00
0!
b1100010 /
1%
1+
#64
0%
0+
#65
b1100001 /
1%
1+
#66
0%
0+
#67
b1100000 /
1%
1+
#68
0%
0+
#69
10
1!
b1011111 /
1%
1+
#70
0%
0+
#71
00
0!
b1011110 /
1%
1+
#72
0%
0+
#73
b1011101 /
1%
1+
#74
0%
0+
#75
b1011100 /
1%
1+
#76
0%
0+
#77
10
1!
b1011011 /
1%
1+
#78
0%
0+
#79
00
0!
b1011010 /
1%
1+
#80
0%
0+
#81
b1011001 /
1%
1+
#82
0%
0+
#83
b1011000 /
1%
1+
#84
0%
0+
#85
10
1!
b1010111 /
1%
1+
#86
0%
0+
#87
00
0!
b1010110 /
1%
1+
#88
0%
0+
#89
b1010101 /
1%
1+
#90
0%
0+
#91
b1010100 /
1%
1+
#92
0%
0+
#93
10
1!
b1010011 /
1%
1+
#94
0%
0+
#95
00
0!
b1010010 /
1%
1+
#96
0%
0+
#97
b1010001 /
1%
1+
#98
0%
0+
#99
b1010000 /
1%
1+
#100
0%
0+
#101
10
1!
b1001111 /
1%
1+
#102
0%
0+
0&
0,
#103
00
0!
b1001110 /
1%
1+
#104
0%
0+
#105
b1001101 /
1%
1+
#106
0%
0+
#107
b1001100 /
1%
1+
#108
0%
0+
#109
10
1!
b1001011 /
1%
1+
#110
0%
0+
#111
b1001010 /
1%
1+
#112
0%
0+
#113
b1001001 /
1%
1+
#114
0%
0+
#115
00
0!
b1001000 /
1%
1+
#116
0%
0+
#117
10
1!
b1000111 /
1%
1+
#118
0%
0+
#119
00
0!
b1000110 /
1%
1+
#120
0%
0+
#121
b1000101 /
1%
1+
#122
0%
0+
#123
b1000100 /
1%
1+
#124
0%
0+
#125
10
1!
b1000011 /
1%
1+
#126
0%
0+
#127
b1000010 /
1%
1+
#128
0%
0+
#129
b1000001 /
1%
1+
#130
0%
0+
#131
00
0!
b1000000 /
1%
1+
#132
0%
0+
#133
10
1!
b111111 /
1%
1+
#134
0%
0+
#135
00
0!
b111110 /
1%
1+
#136
0%
0+
#137
b111101 /
1%
1+
#138
0%
0+
#139
b111100 /
1%
1+
#140
0%
0+
#141
10
1!
b111011 /
1%
1+
#142
0%
0+
#143
b111010 /
1%
1+
#144
0%
0+
#145
b111001 /
1%
1+
#146
0%
0+
#147
00
0!
b111000 /
1%
1+
#148
0%
0+
#149
10
1!
b110111 /
1%
1+
#150
0%
0+
#151
00
0!
b110110 /
1%
1+
#152
0%
0+
#153
b110101 /
1%
1+
#154
0%
0+
#155
b110100 /
1%
1+
#156
0%
0+
#157
10
1!
b110011 /
1%
1+
#158
0%
0+
#159
b110010 /
1%
1+
#160
0%
0+
#161
b110001 /
1%
1+
#162
0%
0+
#163
00
0!
b110000 /
1%
1+
#164
0%
0+
#165
10
1!
b101111 /
1%
1+
#166
0%
0+
#167
00
0!
b101110 /
1%
1+
#168
0%
0+
#169
b101101 /
1%
1+
#170
0%
0+
#171
b101100 /
1%
1+
#172
0%
0+
#173
10
1!
b101011 /
1%
1+
#174
0%
0+
#175
b101010 /
1%
1+
#176
0%
0+
#177
b101001 /
1%
1+
#178
0%
0+
#179
00
0!
b101000 /
1%
1+
#180
0%
0+
#181
10
1!
b100111 /
1%
1+
#182
0%
0+
#183
00
0!
b100110 /
1%
1+
#184
0%
0+
#185
b100101 /
1%
1+
#186
0%
0+
#187
b100100 /
1%
1+
#188
0%
0+
#189
10
1!
b100011 /
1%
1+
#190
0%
0+
#191
00
0!
b100010 /
1%
1+
#192
0%
0+
#193
b100001 /
1%
1+
#194
0%
0+
#195
b100000 /
1%
1+
#196
0%
0+
#197
10
1!
b11111 /
1%
1+
#198
0%
0+
#199
00
0!
b11110 /
1%
1+
#200
0%
0+
#201
b11101 /
1%
1+
#202
0%
0+
#203
b11100 /
1%
1+
#204
0%
0+
#205
b11011 /
1%
1+
#206
0%
0+
#207
b11010 /
1%
1+
#208
0%
0+
#209
b11001 /
1%
1+
#210
0%
0+
#211
b11000 /
1%
1+
#212
0%
0+
#213
b10111 /
1%
1+
#214
0%
0+
#215
b10110 /
1%
1+
#216
0%
0+
#217
b10101 /
1%
1+
#218
0%
0+
#219
b10100 /
1%
1+
#220
0%
0+
#221
b10011 /
1%
1+
#222
0%
0+
#223
b10010 /
1%
1+
#224
0%
0+
#225
b10001 /
1%
1+
#226
0%
0+
#227
b10000 /
1%
1+
#228
0%
0+
#229
b1111 /
1%
1+
#230
0%
0+
#231
b1110 /
1%
1+
#232
0%
0+
#233
b1101 /
1%
1+
#234
0%
0+
#235
b1100 /
1%
1+
#236
0%
0+
#237
b1011 /
1%
1+
#238
0%
0+
#239
b1010 /
1%
1+
#240
0%
0+
#241
b1001 /
1%
1+
#242
0%
0+
#243
b1000 /
1%
1+
#244
0%
0+
#245
b111 /
1%
1+
#246
0%
0+
#247
b110 /
1%
1+
#248
0%
0+
#249
b101 /
1%
1+
#250
0%
0+
#251
b100 /
1%
1+
#252
0%
0+
#253
b11 /
1%
1+
#254
0%
0+
#255
b10 /
1%
1+
#256
0%
0+
#257
b1 /
1%
1+
#258
0%
0+
#259
11
1"
b0 /
1%
1+
